pollination/leed_daylight_option_one/__init__.py
pollination/leed_daylight_option_one/_visualization.py
pollination/leed_daylight_option_one/entry.py
pollination_leed_daylight_option_one-0.1.8.dist-info/LICENSE
pollination_leed_daylight_option_one-0.1.8.dist-info/METADATA
pollination_leed_daylight_option_one-0.1.8.dist-info/WHEEL
pollination_leed_daylight_option_one-0.1.8.dist-info/top_level.txt
pollination_leed_daylight_option_one-0.1.8.dist-info/RECORD
